[
    {
        "id": 1,
        "name": "Cafefeta francesa, calidad premium",
        "price": 7500,
        "description": "Cafetera de vidrio, embolo prensa Francesa 1 L\r\n-rose gold\r\n-negro\r\n-plata\r\n-naranja\r\n-Sabor natural\r\nLa prensa francesa conserva los aceites naturales que los filtros absorben, lo que te permitirá degustar un café de consistencia espesa y deliciosa.",
        "discount": 10,
        "category": "cafeteras",
        "image": [
            "cafeteraFrancesa.jpg"
        ]
    },
    {
        "id": 2,
        "name": "Cafefeta chemex, 6 tazas",
        "price": 12500,
        "description": "Cafetera Chemex classic series CM-6A manual original leather de filtro\r\n-madera clasic\r\n-negro\r\n-madera oscuro\r\nLa mejor opción para cualquier momento del día. Elegí el café molido que más te guste y preparate para vivir una experiencia exquisita.",
        "discount": 10,
        "category": "cafeteras",
        "image": [
            "cafeteraChemex.jpg"
        ]
    },
      {
        "id": 3,
        "name": "Cafetera Volturno Clásica 6 Pocillos manual italiana",
        "price": 10500,
        "description": "Café tradicional\r\nCon un sabor concentrado y un aroma que se apodera de tu casa, tu café moka es el complemento ideal para cualquier momento del día.\r\n-rose gold\r\n-negro\r\n-plata\r\n-celeste",
        "discount": 0,
        "category": "cafeteras",
        "image": [
            "voulturno.jpg"
        ]
    },
    {
        "id": 4,
        "name": "Cafetera filtro reutilizable, Jarra 1,2 Lts",
        "price": 6500,
        "description": "Sistema antigoteo para servir una taza de café cuando quiera\r\nEl sistema antigoteo le permite servir una taza de café antes de que termine el ciclo de preparación completo.\r\nCon esta cafetera se pueden preparar entre 2 y 10 (tazas grandes)/15 (tazas pequeñas) de café. Tiene un máximo de 1,2 litros.\r\n-negro\r\n-plata",
        "discount": 10,
        "category": "cafeteras",
        "image": [
            "cafeteraFiltro.jpg"
        ]
    },
    {
        "id": 5,
        "name": "Molinillo de cafe manual, Amoladora de cafe acero inoxidable",
        "price": 4500,
        "description": "No se necesitan baterías, energía ni cables largos de plástico para operar su molinillo portátil, lo que le permite viajar y preparar granos de café molidos recién tostados en su próximo campamento, excursionismo, mochila o viaje al aire libre.\r\nMolino manual con muelas de cerámica.\r\n-negro\r\n-plata\r\n-celeste",
        "discount": 10,
        "category": "accesorios",
        "image": [
            "molinillo.webp"
        ]
    },
    {
        "id": 6,
        "name": "Capsulas para cafetera recargable +300",
        "price": 2500,
        "description": "Capsulas recargables para máquina Dolce Gusto + 1 cucharita medidora 100% compatible reutilizable mas de 100 veces\r\n-negro\r\n-verde\r\n-plata\r\n-turquesa",
        "discount": 0,
        "category": "3",
        "subcategory": "accesorios",
        "image": [
            "recargable.jpg"
        ]
    },
    {
        "id": 7,
        "name": "Taza cerámica ARTE CAFE 250ml",
        "price": 750,
        "description": "",
        "discount": 10,
        "category": "Accesorios",
        "image": [
            "tazaBlanca.jpg"
        ]
    },
    {
        "id": 8,
        "name": "Granos de café tostado organico sin moler, 250gr",
        "price": 400,
        "description": "Cafetera de vidrio, embolo prensa Francesa 1 L\r\n-rose gold\r\n-negro\r\n-plata\r\n-marron",
        "discount": 15,
        "category": "cafe",
        "image": [
            "granosCafe.jpg"
        ]
    },
    {
        "id": 9,
        "name": "Café artesanal, molido en el momento, bolsa 400gr",
        "price": 500,
        "description": "Espresso Napoli, mezcla Signature, es un espresso lleno de sabor y bien balanceado de fuerte carácter e intenso sabor. El proceso de tostado oscuro en conjunto con el suelo rico en nutrientes de Sudámerica, le otorga a los granos de café un sabor de nueces con un toque de cocoa.",
        "discount": 25,
        "category": "cafe",
        "image": [
            "cafe_artesanal.jpg"
        ]
    },
    {
        "id": 10,
        "name": "Café molido premiun intenso 500gr",
        "price": 1200,
        "description": "El café de origen único Colombia es reconocible por su envolvente e intenso sabor. Los granos de café son obtenidos de agricultores independientes y en condiciones Fairtrade. Intensidad 5 de 8.",
        "discount": 25,
        "category": "cafe",
        "image": [
            "bolsa_negra.jpg"
        ]
    },
    {
        "id": 11,
        "name": "Café tostado en grano premium 250gr",
        "price": 650,
        "description": "Espresso Verona es siempre un favorito dentro de la variedad de Real Coffee, el auténtico sabor del espresso oscuro tostado italiano, con una consistencia compleja y densa. Es ideal para café latte, macchiato o un buen cortado",
        "discount": 20,
        "category": "cafe",
        "image": [
            "coffee_intens.jpg"
        ]
    },
    {
        "id": 12,
        "name": "Combo café de estación dos bolsas 450gr c/u",
        "price": 1200,
        "description": "Blend elaborado con granos de café arábica Supremo, variedad Caturra- Catuaí, seleccionados de las mejores fincas de Colombia, cosechados a 1600 metros de altura. Posee características suaves, sabor balanceado, con notas frutales, leve acidez y cuerpo medio muy aromático, para ser disfrutado en todo momento\n Destacan por sus colores intensos y por un especial proceso de encolado que hace que las minas sean súper resistentes a la rotura. \n Podes seleccionar en la publicación el tipo de molido de tu preferencia, indicándonos el tipo de cafetera. SE MUELE EN EL DIA ANTES DE ENVIARLO.",
        "discount": 20,
        "category": "cafe",
        "image": [
            "combo.png"
        ]
    },
    {
        "id": 13,
        "name": "Cafetera AeroPress",
        "price": 4300,
        "description": "Sistema antigoteo para servir una taza de café cuando quiera\r\nEl sistema antigoteo le permite servir una taza de café antes de que termine el ciclo de preparación completo.\r\nCon esta cafetera se pueden preparar entre 2 y 10 (tazas grandes)/15 (tazas pequeñas) de café. Tiene un máximo de 1,2 litros.\r\n-negro\r\n-plata",
        "discount": 0,
        "category": "cafeteras",
        "image": [
            "aeropress.webp"
        ]
    },
    {
        "id": 14,
        "name": "Filtros de papel tipo Canasta",
        "price": 280,
        "description": "Aptos para todo tipo de cafeteras eléctricas con portafiltros 'canasta' ",
        "discount": 0,
        "category": "accesorio",
        "image": [
            "filtro.jpg"
        ]
    },
    {
        "id": 15,
        "name": "Termometro Con Pinza Para Baristas",
        "price": 1195,
        "description": "Aliado perfecto de todo Barista a la hora de servir un buen café. La temperatura de la leche debe alcanzar una medida de 65-70ªC para una espuma perfecta (y un arte latte garantizado)",
        "discount": 0,
        "category": "accesorios",
        "image": [
            "termometro.webp"
        ]
    },
     {
        "id": 16,
        "name": "Pava Barista Café - Tetera Kettle Cuello De Cisne 1 Lt",
        "price": 5200,
        "description": "Tetera de acero inoxidable de fácil uso. Ofrece un pico delgado para facilitar el vertido del agua en la preparación de tu café .Exclusivo pico fino y alargado que te permitirá controlar perfectamente la ubicación y el flujo de agua que vierte sobre el café. Es apto para fuego directo, vitrocerámica e inducción.",
        "discount": 0,
        "category": "accesorios",
        "image": [
            "tetera.jpg"
        ]
    },
    {
        "id": 17,
        "name": "Vaso Con Tapa Y Sorbete Acrilico  Termico",
        "price": 600,
        "description": "Vaso de Acrilico Frio/Calor - Doble Pared, Tapa a Rosca con sello interno para cierre hermetico Sorbete Color Blanco - No descartable",
        "discount": 0,
        "category": "accesorios",
        "image": [
            "vasoTransparente.jpg"
        ]
    }, 
    {
        "id": 18,
        "name": "Balanza Cafe Scale Barista Digital C/ Temporizador Infusores",
        "price": 9000,
        "description": "Balanza Digital ideal para baristas o para complemento de Cocina.",
        "discount": 10,
        "category": "accesorios",
        "image": [
            "balanza scale digital.webp"
        ]
    },
    {
        "id": 19,
        "name": "Cafe Torrado Molido Intenso ARTE CAFE X 1 Kg",
        "price": 900,
        "description": "Sabor delicado, profundo y pronunciado con un aroma fuerte y persistente.",
        "discount": 0,
        "category": "cafe",
        "image": [
            "coffee_intens.jpg"
        ]
    }, {
        "id": 20,
        "name": "Jarro Térmico con Tapa Base ARTE CAFE",
        "price": 1080,
        "description": "Están diseñados con doble capa plástica de alta resistencia para que no te quemes.",
        "discount": 10,
        "category": "accesorios",
        "image": [
            "jarronMetal.jpg"
        ]
    }
]